mcp_multi_weather/__init__.py
mcp_multi_weather/mcp.py
mcp_multi_weather/py.typed
mcp_multi_weather/cli/dxt_manifest.py
mcp_multi_weather/cli/server.py
mcp_multi_weather/components/__init__.py
mcp_multi_weather/components/weather.py
mcp_multi_weather/providers/__init__.py
mcp_multi_weather/providers/base.py
mcp_multi_weather/providers/openweather.py
mcp_multi_weather/providers/types.py
mcp_multi_weather-0.2.1.dist-info/METADATA
mcp_multi_weather-0.2.1.dist-info/WHEEL
mcp_multi_weather-0.2.1.dist-info/entry_points.txt
mcp_multi_weather-0.2.1.dist-info/RECORD
