Metadata-Version: 2.4
Name: mcp-multi-weather
Version: 0.2.1
Summary: MCP server for checking the weather history and forecast
Project-URL: Homepage, https://github.com/igalarzab/mcp-multi-weather
Author-email: Jose Galarza <igalarzab@gmail.com>
License-Expression: MIT
Requires-Python: >=3.12
Requires-Dist: aiohttp[speedups]>=3.12.14
Requires-Dist: dotenv>=0.9.9
Requires-Dist: fastmcp>=2.10.6
